fastapi_users_db_opensearch/__init__.py
fastapi_users_db_opensearch/py.typed
fastapi_users_db_opensearch-0.0.4.dist-info/LICENSE
fastapi_users_db_opensearch-0.0.4.dist-info/WHEEL
fastapi_users_db_opensearch-0.0.4.dist-info/METADATA
fastapi_users_db_opensearch-0.0.4.dist-info/RECORD
