Metadata-Version: 2.1
Name: fastapi-users-db-opensearch
Version: 0.0.4
Summary: FastAPI Users database adapter for OpenSearch.
Home-page: https://github.com/KentonParton/fastapi-users-db-opensearch
Author: Kenton Parton
Author-email: kparton@swiple.io
Requires-Python: >=3.7
Classifier: License :: OSI Approved :: MIT License
Classifier: Development Status :: 5 - Production/Stable
Classifier: Framework :: AsyncIO
Classifier: Intended Audience :: Developers
Classifier: Programming Language :: Python :: 3.7
Classifier: Programming Language :: Python :: 3.8
Classifier: Programming Language :: Python :: 3.9
Classifier: Programming Language :: Python :: 3 :: Only
Classifier: Topic :: Internet :: WWW/HTTP :: Session
Requires-Dist: fastapi-users >= 9.1.0,<10.0.0
Project-URL: Documentation, https://github.com/KentonParton/fastapi-users-db-opensearch
